oseg/__init__.py
oseg/oseg.py
oseg-0.3.dev0.dist-info/licenses/LICENSE
oseg-0.3.dev0.dist-info/METADATA
oseg-0.3.dev0.dist-info/WHEEL
oseg-0.3.dev0.dist-info/top_level.txt
oseg-0.3.dev0.dist-info/RECORD
