Metadata-Version: 2.4
Name: oseg
Version: 0.3.dev0
Summary: OpenAPI SDK Example Generator
Author-email: Juan Treminio <jtreminio@gmail.com>
Project-URL: Documentation, https://github.com/jtreminio/oseg/blob/main/README.md
Project-URL: Issues, https://github.com/jtreminio/oseg/issues
Project-URL: Source, https://github.com/jtreminio/oseg
Keywords: OpenAPI,openapi-generator,sdk
Classifier: Development Status :: 4 - Beta
Requires-Python: >=3.13
License-File: LICENSE
Requires-Dist: Jinja2~=3.1
Requires-Dist: openapi-pydantic~=0.5
Requires-Dist: pydantic~=2.10
Requires-Dist: PyYAML~=6.0
Requires-Dist: click~=8.1
Requires-Dist: tabulate~=0.9
Dynamic: license-file
